winpackit.py
WinPackIt-0.8.0.dist-info/LICENSE
WinPackIt-0.8.0.dist-info/METADATA
WinPackIt-0.8.0.dist-info/WHEEL
WinPackIt-0.8.0.dist-info/top_level.txt
WinPackIt-0.8.0.dist-info/RECORD
