Metadata-Version: 2.1
Name: WinPackIt
Version: 0.8.0
Summary: The quick and dirty Python packager for Windows
Home-page: https://github.com/ricpol/winpackit
Author: Riccardo Polignieri
License: UNKNOWN
Project-URL: Source, https://github.com/ricpol/winpackit
Project-URL: Docs, https://github.com/ricpol/winpackit/blob/master/docs.rst
Keywords: packaging build development
Platform: UNKNOWN
Classifier: Development Status :: 3 - Alpha
Classifier: Environment :: Console
Classifier: Intended Audience :: Developers
Classifier: Topic :: Software Development :: Build Tools
Classifier: License :: OSI Approved :: MIT License
Classifier: Programming Language :: Python :: 3.5
Classifier: Programming Language :: Python :: 3.6
Classifier: Programming Language :: Python :: 3.7
Classifier: Programming Language :: Python :: 3.8
Classifier: Programming Language :: Python :: 3.9
Classifier: Programming Language :: Python :: 3.10
Classifier: Operating System :: Microsoft :: Windows
Requires-Python: >=3.6
